lstcam_calib/__init__.py
lstcam_calib/_version.py
lstcam_calib/conftest.py
lstcam_calib/statistics.py
lstcam_calib/version.py
lstcam_calib/drs4/__init__.py
lstcam_calib/drs4/time_correction_calculator.py
lstcam_calib/io/__init__.py
lstcam_calib/io/calibration.py
lstcam_calib/io/database.py
lstcam_calib/io/metadata.py
lstcam_calib/io/tests/test_database.py
lstcam_calib/onsite/__init__.py
lstcam_calib/onsite/onsite_create_calibration_file.py
lstcam_calib/onsite/onsite_create_calibration_files_with_batch.py
lstcam_calib/onsite/onsite_create_cat_b_calibration_file.py
lstcam_calib/onsite/onsite_create_cat_b_calibration_files_with_batch.py
lstcam_calib/onsite/onsite_create_drs4_pedestal_file.py
lstcam_calib/onsite/onsite_create_drs4_time_file.py
lstcam_calib/onsite/onsite_create_drs4_timelapse_file.py
lstcam_calib/onsite/onsite_create_fit_intensity_scan_file.py
lstcam_calib/onsite/tests/test_onsite.py
lstcam_calib/onsite/tests/test_onsite_scripts.py
lstcam_calib/pixel/__init__.py
lstcam_calib/pixel/calibration_calculator.py
lstcam_calib/pixel/flatfield.py
lstcam_calib/pixel/pedestals.py
lstcam_calib/pixel/utils.py
lstcam_calib/pixel/tests/__init__.py
lstcam_calib/pixel/tests/test_calculator.py
lstcam_calib/pixel/tests/test_flatfield.py
lstcam_calib/pixel/tests/test_pedestals.py
lstcam_calib/resources/catA_camera_calibration_param.yml
lstcam_calib/resources/catB_camera_calibration_param.yml
lstcam_calib/resources/filters_transmission.dat
lstcam_calib/resources/fit_intensity_scan_config_example.yml
lstcam_calib/resources/npe_std_noise_parameters.yml
lstcam_calib/tests/__init__.py
lstcam_calib/tests/test_statistics.py
lstcam_calib/tests/test_version.py
lstcam_calib/tools/__init__.py
lstcam_calib/tools/aggregate_drs4_timelapse_data.py
lstcam_calib/tools/change_database_document.py
lstcam_calib/tools/create_calibration_file.py
lstcam_calib/tools/create_cat_b_calibration_file.py
lstcam_calib/tools/create_drs4_pedestal_file.py
lstcam_calib/tools/create_drs4_time_file.py
lstcam_calib-0.3.1.dist-info/licenses/LICENSE
lstcam_calib-0.3.1.dist-info/METADATA
lstcam_calib-0.3.1.dist-info/WHEEL
lstcam_calib-0.3.1.dist-info/entry_points.txt
lstcam_calib-0.3.1.dist-info/top_level.txt
lstcam_calib-0.3.1.dist-info/RECORD
