Metadata-Version: 2.4
Name: lstcam_calib
Version: 0.3.1
Summary: Camera calibration code for the LSTCam
Author-email: Franca Cassol <cassol@cppm.in2p3.fr>, Maximilian Linhoff <maximilian.linhoff@tu-dortmund.de>
License: BSD-3-Clause
Project-URL: repository, https://gitlab.cta-observatory.org/cta-array-elements/lst/analysis/lstcam_calib/
Requires-Python: >=3.10
License-File: LICENSE
Requires-Dist: numpy
Requires-Dist: ctapipe~=0.26.0
Requires-Dist: ctapipe_io_lst<0.28.0a0,>=0.26.0
Requires-Dist: protozfits<3,>=2.6
Requires-Dist: matplotlib
Requires-Dist: eventio~=1.16
Requires-Dist: iminuit
Requires-Dist: pymongo
Requires-Dist: pydantic
Requires-Dist: jsonschema
Provides-Extra: test
Requires-Dist: pytest; extra == "test"
Requires-Dist: pytest-cov; extra == "test"
Requires-Dist: pytest-order; extra == "test"
Provides-Extra: doc
Requires-Dist: sphinx; extra == "doc"
Requires-Dist: numpydoc; extra == "doc"
Requires-Dist: pydata-sphinx-theme; extra == "doc"
Requires-Dist: sphinx-automodapi; extra == "doc"
Requires-Dist: sphinx-argparse; extra == "doc"
Requires-Dist: sphinx-design; extra == "doc"
Requires-Dist: sphinxcontrib-bibtex; extra == "doc"
Requires-Dist: sphinx-exec-code; extra == "doc"
Requires-Dist: nbsphinx; extra == "doc"
Requires-Dist: ipykernel; extra == "doc"
Requires-Dist: autodoc_pydantic; extra == "doc"
Requires-Dist: sphinx-changelog; extra == "doc"
Provides-Extra: dev
Requires-Dist: setuptools_scm; extra == "dev"
Requires-Dist: towncrier; extra == "dev"
Dynamic: license-file
